tastymotion/__init__.py
tastymotion-0.0.0.dist-info/METADATA
tastymotion-0.0.0.dist-info/WHEEL
tastymotion-0.0.0.dist-info/top_level.txt
tastymotion-0.0.0.dist-info/RECORD
