Metadata-Version: 2.2
Name: tastymotion
Version: 0.0.0
Summary: Coming soon
Author-email: dev727 <dev727@tastymotion.com>
